sfdata/__init__.py
sfdata/converter.py
sfdata/datastore/__init__.py
sfdata/datastore/_store.py
sfdata/datastore/_table.py
sfdata/datastore/_table_key.py
sfdata/datastore/_table_row.py
sfdata/exporter.py
sfdata/identifier.py
sfdata/normaliser.py
sfdata/schema/__init__.py
sfdata/schema/_data.py
sfdata/schema/_proxy.py
sfdata/schema/_types.py
sfdata/schema/erd/__init__.py
sfdata/schema/erd/templates/erd.dot
sfdata/schema/parser/__init__.py
sfdata/settings.py
sfdata/standardiser.py
sfdata/stream_parser/__init__.py
sfdata/stream_parser/checks.py
sfdata/stream_parser/collectors.py
sfdata/stream_parser/events.py
sfdata/stream_parser/filters/__init__.py
sfdata/stream_parser/filters/column_headers.py
sfdata/stream_parser/filters/context.py
sfdata/stream_parser/filters/generic.py
sfdata/stream_parser/filters/types.py
sfdata/stream_parser/function_helpers.py
sfdata/stream_parser/functions.py
sfdata/stream_parser/parser/__init__.py
sfdata/stream_parser/parser/csv.py
sfdata/stream_parser/parser/openpyxl.py
sfdata/stream_parser/parser/xml.py
sfdata/stream_parser/stream.py
sfdata/stream_parser/types.py
sfdata-0.1.3.dist-info/METADATA
sfdata-0.1.3.dist-info/WHEEL
sfdata-0.1.3.dist-info/RECORD
