Metadata-Version: 2.1
Name: sfdata
Version: 0.1.3
Summary: 
Author: franciscobmacedo
Author-email: franciscovcbm@gmail.com
Requires-Python: >=3.10,<4.0
Classifier: Programming Language :: Python :: 3
Classifier: Programming Language :: Python :: 3.10
Classifier: Programming Language :: Python :: 3.11
Provides-Extra: pandas
Requires-Dist: jstyleson (>=0.0.2,<0.0.3)
Requires-Dist: lxml (>=4.9.3,<5.0.0)
Requires-Dist: more-itertools (>=10.0.0,<11.0.0)
Requires-Dist: openpyxl (>=3.1.2,<4.0.0)
Requires-Dist: pandas (>=2.0.3,<3.0.0) ; extra == "pandas"
Requires-Dist: pydantic (>=2.1.1,<3.0.0)
Requires-Dist: pyhumps (>=3.8.0,<4.0.0)
Requires-Dist: pyyaml (>=6.0.1,<7.0.0)
Requires-Dist: tablib (>=3.5.0,<4.0.0)
Requires-Dist: xsdata (>=23.7,<24.0)
